<?xml version="1.0" encoding="UTF-8" ?>
<cameras>
	<camera>
        <id>550</id>
		<lat>40.363998</lat>
		<lng>-80.11875</lng>
	</camera>
	<camera>
        <id>555</id>
		<lat>40.369420000000005</lat>
		<lng>-80.11842</lng>
	</camera>
	<camera>
        <id>560</id>
		<lat>40.37228</lat>
		<lng>-80.11036</lng>
	</camera>
	<camera>
        <id>565</id>
		<lat>40.373823</lat>
		<lng>-80.103885</lng>
	</camera>
	<camera>
        <id>570</id>
		<lat>40.381718</lat>
		<lng>-80.096462</lng>
	</camera>
	<camera>
        <id>575</id>
		<lat>40.388484</lat>
		<lng>-80.098403</lng>
	</camera>
	<camera>
        <id>580</id>
		<lat>40.393255</lat>
		<lng>-80.100679</lng>
	</camera>
	<camera>
        <id>585</id>
		<lat>40.399028</lat>
		<lng>-80.105154</lng>
	</camera>
	<camera>
        <id>590</id>
		<lat>40.407167</lat>
		<lng>-80.107378</lng>
	</camera>
	<camera>
        <id>595</id>
		<lat>40.414122</lat>
		<lng>-80.104731</lng>
	</camera>
</cameras>
